oat/__about__.py
oat/__init__.py
oat/args.py
oat/exploration.py
oat/interface.py
oat/model.py
oat/multistep.py
oat/prompts.py
oat/types.py
oat/actors/__init__.py
oat/actors/base.py
oat/actors/preference.py
oat/actors/reward.py
oat/algorithms/__init__.py
oat/algorithms/apl.py
oat/algorithms/ppo.py
oat/algorithms/ppo_multiturn.py
oat/algorithms/rft.py
oat/algorithms/xpo.py
oat/collectors/__init__.py
oat/collectors/asynchronous.py
oat/collectors/base.py
oat/experiment/__init__.py
oat/experiment/main.py
oat/experiment/run_apl.py
oat/experiment/run_math_rl.py
oat/experiment/run_offline.py
oat/experiment/run_offline_lp.py
oat/experiment/run_offline_ppo.py
oat/experiment/run_ppo.py
oat/experiment/run_xpo.py
oat/learners/__init__.py
oat/learners/base.py
oat/learners/dap.py
oat/learners/dap_with_rm.py
oat/learners/loss.py
oat/learners/ntp.py
oat/learners/offline.py
oat/learners/offline_dap.py
oat/learners/rl.py
oat/learners/sft.py
oat/oracles/__init__.py
oat/oracles/base.py
oat/oracles/countdown.py
oat/oracles/gpt.py
oat/oracles/math.py
oat/oracles/remote/__init__.py
oat/oracles/remote/client.py
oat/oracles/remote/server.py
oat/rm/__init__.py
oat/rm/backbone.py
oat/rm/model.py
oat/rm/networks.py
oat/rm/uncertainty.py
oat/utils/__init__.py
oat/utils/buffer.py
oat/utils/data.py
oat/utils/deepspeed.py
oat/utils/distributed.py
oat/utils/ipc.py
oat/utils/launcher.py
oat/utils/lm_head.py
oat/utils/math_grader.py
oat/utils/ops.py
oat/utils/slicer.py
oat_llm-0.2.4.dist-info/LICENSE
oat_llm-0.2.4.dist-info/METADATA
oat_llm-0.2.4.dist-info/WHEEL
oat_llm-0.2.4.dist-info/top_level.txt
oat_llm-0.2.4.dist-info/RECORD
