Metadata-Version: 2.1
Name: oat-llm
Version: 0.2.4
Summary: Online AlignmenT (OAT) for LLMs.
Home-page: https://github.com/sail-sg/oat
Author: Zichen Liu
Author-email: Zichen Liu <liuzc@sea.com>, Xinyi Wan <wanxy@sea.com>, Changyu Chen <chency@sea.com>
License: Apache-2.0
Project-URL: Documentation, https://github.com/sail-sg/oat#readme
Project-URL: Issues, https://github.com/sail-sg/oat/issues
Project-URL: Source, https://github.com/sail-sg/oat
Keywords: rlhf,llm reasoning,llm,ai-alignment,rl,bandit,ai,sample-efficiency
Classifier: Development Status :: 4 - Beta
Classifier: Programming Language :: Python
Classifier: Programming Language :: Python :: 3.10
Classifier: Programming Language :: Python :: Implementation :: CPython
Classifier: Programming Language :: Python :: Implementation :: PyPy
Requires-Python: >=3.8, <3.11
License-File: LICENSE
Requires-Dist: accelerate
Requires-Dist: bitsandbytes
Requires-Dist: datasets
Requires-Dist: deepspeed==0.16.8
Requires-Dist: dm-launchpad[tensorflow]
Requires-Dist: einops
Requires-Dist: flash-attn==2.7.4.post1
Requires-Dist: fire
Requires-Dist: httpx
Requires-Dist: jsonlines
Requires-Dist: loralib
Requires-Dist: ml-collections
Requires-Dist: mosec
Requires-Dist: msgspec
Requires-Dist: optimum
Requires-Dist: packaging
Requires-Dist: peft==0.15.2
Requires-Dist: protobuf==3.20.0
Requires-Dist: pyarrow<12,>=0.6.1
Requires-Dist: python-Levenshtein==0.25.1
Requires-Dist: scipy
Requires-Dist: torchmetrics
Requires-Dist: tqdm
Requires-Dist: tyro
Requires-Dist: transformers==4.51.3
Requires-Dist: transformers-stream-generator
Requires-Dist: vllm==0.8.4
Requires-Dist: rich
Requires-Dist: wandb
Requires-Dist: wheel
Requires-Dist: numpy==1.26.4
Requires-Dist: math-verify[antlr4_13_2]
Requires-Dist: pylatexenc==2.10
